engineio_v3/__init__.py
engineio_v3/asyncio_client.py
engineio_v3/asyncio_server.py
engineio_v3/asyncio_socket.py
engineio_v3/client.py
engineio_v3/exceptions.py
engineio_v3/middleware.py
engineio_v3/packet.py
engineio_v3/payload.py
engineio_v3/server.py
engineio_v3/socket.py
engineio_v3/static_files.py
engineio_v3/async_drivers/__init__.py
engineio_v3/async_drivers/aiohttp.py
engineio_v3/async_drivers/asgi.py
engineio_v3/async_drivers/eventlet.py
engineio_v3/async_drivers/gevent.py
engineio_v3/async_drivers/gevent_uwsgi.py
engineio_v3/async_drivers/sanic.py
engineio_v3/async_drivers/threading.py
engineio_v3/async_drivers/tornado.py
python_engineio_v3-3.14.2.dist-info/LICENSE
python_engineio_v3-3.14.2.dist-info/METADATA
python_engineio_v3-3.14.2.dist-info/WHEEL
python_engineio_v3-3.14.2.dist-info/top_level.txt
python_engineio_v3-3.14.2.dist-info/RECORD
